datafactoryfc/__init__.py
datafactoryfc/exceptions.py
datafactoryfc/functions.py
datafactoryfc/assets/xTGrid.json
datafactoryfc-1.0.7.dist-info/METADATA
datafactoryfc-1.0.7.dist-info/WHEEL
datafactoryfc-1.0.7.dist-info/top_level.txt
datafactoryfc-1.0.7.dist-info/RECORD
