Metadata-Version: 2.1
Name: datafactoryfc
Version: 1.0.7
Summary: Scrape football data from DataFactory
Home-page: https://www.github.com/valensantarone/datafactory
Author: Valko
Author-email: valensantarone@gmail.com
Classifier: Programming Language :: Python :: 3
Classifier: License :: OSI Approved :: MIT License
Classifier: Operating System :: OS Independent
Requires-Python: >=3.6
Requires-Dist: importlib
Requires-Dist: requests
Requires-Dist: pandas
Requires-Dist: numpy
